quickcrud/__init__.py
quickcrud/cli.py
quickcrud/crud_generator.py
quickcrud/docker_generator.py
quickcrud/sql_parser.py
quickcrud-0.1.0.dist-info/LICENSE
quickcrud-0.1.0.dist-info/METADATA
quickcrud-0.1.0.dist-info/WHEEL
quickcrud-0.1.0.dist-info/entry_points.txt
quickcrud-0.1.0.dist-info/RECORD
