Metadata-Version: 2.1
Name: quickcrud
Version: 0.1.0
Summary: CLI to automatically generate FastAPI APIs from a SQL schema.
Home-page: https://github.com/wendersoon/QuickCRUD
License: MIT
Keywords: fastapi,crud,sql,docker
Author: Wenderson
Author-email: ds.wendersonmelo@gmail.com
Requires-Python: >=3.12,<4.0
Classifier: License :: OSI Approved :: MIT License
Classifier: Programming Language :: Python :: 3
Classifier: Programming Language :: Python :: 3.12
Requires-Dist: click (>=8.1.7,<9.0.0)
Requires-Dist: fastapi (>=0.115.5,<0.116.0)
Requires-Dist: sqlalchemy (>=2.0.36,<3.0.0)
Requires-Dist: sqlparse (>=0.5.2,<0.6.0)
Requires-Dist: uvicorn (>=0.32.0,<0.33.0)
Project-URL: Repository, https://github.com/wendersoon/QuickCRUD
